pymontecarlo/__init__.py
pymontecarlo/__main__.py
pymontecarlo/_version.py
pymontecarlo/entity.py
pymontecarlo/exceptions.py
pymontecarlo/mock.py
pymontecarlo/project.py
pymontecarlo/settings.py
pymontecarlo/simulation.py
pymontecarlo/figures/__init__.py
pymontecarlo/figures/base.py
pymontecarlo/figures/sample.py
pymontecarlo/formats/__init__.py
pymontecarlo/formats/base.py
pymontecarlo/formats/dataframe.py
pymontecarlo/formats/document.py
pymontecarlo/formats/identifier.py
pymontecarlo/formats/series.py
pymontecarlo/options/__init__.py
pymontecarlo/options/base.py
pymontecarlo/options/composition.py
pymontecarlo/options/material.py
pymontecarlo/options/options.py
pymontecarlo/options/particle.py
pymontecarlo/options/xrayline.py
pymontecarlo/options/analysis/__init__.py
pymontecarlo/options/analysis/base.py
pymontecarlo/options/analysis/kratio.py
pymontecarlo/options/analysis/photon.py
pymontecarlo/options/analysis/photonintensity.py
pymontecarlo/options/beam/__init__.py
pymontecarlo/options/beam/base.py
pymontecarlo/options/beam/cylindrical.py
pymontecarlo/options/beam/gaussian.py
pymontecarlo/options/beam/pencil.py
pymontecarlo/options/detector/__init__.py
pymontecarlo/options/detector/base.py
pymontecarlo/options/detector/photon.py
pymontecarlo/options/model/__init__.py
pymontecarlo/options/model/base.py
pymontecarlo/options/model/bremsstrahlung_emission.py
pymontecarlo/options/model/direction_cosine.py
pymontecarlo/options/model/elastic_cross_section.py
pymontecarlo/options/model/energy_loss.py
pymontecarlo/options/model/fluorescence.py
pymontecarlo/options/model/inelastic_cross_section.py
pymontecarlo/options/model/ionization_cross_section.py
pymontecarlo/options/model/ionization_potential.py
pymontecarlo/options/model/mass_absorption_coefficient.py
pymontecarlo/options/model/photon_scattering_cross_section.py
pymontecarlo/options/model/random_number_generator.py
pymontecarlo/options/program/__init__.py
pymontecarlo/options/program/base.py
pyMonteCarlo-1.1.0.dist-info/LICENSE
pyMonteCarlo-1.1.0.dist-info/METADATA
pyMonteCarlo-1.1.0.dist-info/WHEEL
pyMonteCarlo-1.1.0.dist-info/top_level.txt
pyMonteCarlo-1.1.0.dist-info/RECORD
