Metadata-Version: 2.1
Name: pyMonteCarlo
Version: 1.1.0
Summary: Python interface for Monte Carlo simulation programs
Home-page: https://github.com/pymontecarlo
Author: Philippe T. Pinard, Hendrix Demers, Raynald Gauvin and Silvia Richter
Author-email: philippe.pinard@gmail.com
Maintainer: Philippe T. Pinard
Maintainer-email: philippe.pinard@gmail.com
License: Apache License version 2.0
Platform: UNKNOWN
Classifier: Development Status :: 4 - Beta
Classifier: Intended Audience :: End Users/Desktop
Classifier: License :: OSI Approved :: GNU General Public License (GPL)
Classifier: Natural Language :: English
Classifier: Programming Language :: Python
Classifier: Operating System :: OS Independent
Classifier: Topic :: Scientific/Engineering
Classifier: Topic :: Scientific/Engineering :: Physics
License-File: LICENSE
Requires-Dist: docutils
Requires-Dist: h5py
Requires-Dist: matplotlib
Requires-Dist: more-itertools
Requires-Dist: numpy
Requires-Dist: pandas
Requires-Dist: pint
Requires-Dist: psutil
Requires-Dist: pyparsing
Requires-Dist: pyxray
Requires-Dist: tqdm
Requires-Dist: uncertainties
